aiida_hubbard/__init__.py
aiida_hubbard/calculations/__init__.py
aiida_hubbard/calculations/hp.py
aiida_hubbard/calculations/functions/__init__.py
aiida_hubbard/calculations/functions/structure_relabel_kinds.py
aiida_hubbard/calculations/functions/structure_reorder_kinds.py
aiida_hubbard/cli/__init__.py
aiida_hubbard/cli/calculations/__init__.py
aiida_hubbard/cli/calculations/hp.py
aiida_hubbard/cli/workflows/__init__.py
aiida_hubbard/cli/workflows/hubbard.py
aiida_hubbard/cli/workflows/hp/__init__.py
aiida_hubbard/cli/workflows/hp/base.py
aiida_hubbard/cli/workflows/hp/main.py
aiida_hubbard/parsers/__init__.py
aiida_hubbard/parsers/hp.py
aiida_hubbard/parsers/parse_raw/__init__.py
aiida_hubbard/parsers/parse_raw/hp.py
aiida_hubbard/utils/__init__.py
aiida_hubbard/utils/general.py
aiida_hubbard/utils/validation.py
aiida_hubbard/workflows/__init__.py
aiida_hubbard/workflows/hubbard.py
aiida_hubbard/workflows/hp/__init__.py
aiida_hubbard/workflows/hp/base.py
aiida_hubbard/workflows/hp/main.py
aiida_hubbard/workflows/hp/parallelize_atoms.py
aiida_hubbard/workflows/hp/parallelize_qpoints.py
aiida_hubbard/workflows/protocols/__init__.py
aiida_hubbard/workflows/protocols/hubbard.yaml
aiida_hubbard/workflows/protocols/hp/__init__.py
aiida_hubbard/workflows/protocols/hp/base.yaml
aiida_hubbard/workflows/protocols/hp/main.yaml
aiida_hubbard-0.5.0.dist-info/entry_points.txt
aiida_hubbard-0.5.0.dist-info/licenses/LICENSE.txt
aiida_hubbard-0.5.0.dist-info/WHEEL
aiida_hubbard-0.5.0.dist-info/METADATA
aiida_hubbard-0.5.0.dist-info/RECORD
